discord_api_types/__init__.py
discord_api_types/errors.py
discord_api_types/gateway.py
discord_api_types/http.py
discord_api_types-0.0.7.dist-info/LICENSE
discord_api_types-0.0.7.dist-info/METADATA
discord_api_types-0.0.7.dist-info/WHEEL
discord_api_types-0.0.7.dist-info/top_level.txt
discord_api_types-0.0.7.dist-info/RECORD
