Metadata-Version: 2.1
Name: discord-api-types
Version: 0.0.7
Summary: This is discord-api low wrapper.
Home-page: https://github.com/discord-api-py-org/discord-api-types
Author: DMS
Author-email: masato190411@gmail.com
License: UNKNOWN
Project-URL: Documentation, https://discord-api-py-org.github.io/document/
Platform: UNKNOWN
Classifier: Programming Language :: Python :: 3.8
Classifier: License :: OSI Approved :: MIT License
Classifier: Operating System :: OS Independent
Requires-Dist: aiohttp (>=3.7.4)
Provides-Extra: speed
Requires-Dist: ujson (>=1.35) ; extra == 'speed'
Requires-Dist: uvloop (>=0.5.3) ; extra == 'speed'
